pokeport/__init__.py
pokeport/__main__.py
pokeport/pokeport.py
pokeport/requirements.txt
pokeport-1.0.0.dist-info/METADATA
pokeport-1.0.0.dist-info/WHEEL
pokeport-1.0.0.dist-info/entry_points.txt
pokeport-1.0.0.dist-info/licenses/LICENSE
pokeport-1.0.0.dist-info/RECORD
