Metadata-Version: 2.4
Name: pokeport
Version: 1.0.0
Summary: A Python script that queries SpriteCollab and returns prints a portrait of a Pokémon to the terminal.
Project-URL: Homepage, https://github.com/Deeshura/pokeport
Project-URL: Issues, https://github.com/Deeshura/pokeport/issues
Author-email: Deeshura <dukeashura@gmail.com>
License-Expression: MIT
License-File: LICENSE
Classifier: Operating System :: OS Independent
Classifier: Programming Language :: Python :: 3
Requires-Python: >=3.9
Requires-Dist: aiohttp>=3.11.16
Requires-Dist: climage>=0.2.2
Requires-Dist: gql~=3.5.2
Requires-Dist: pillow>=11.2.1
Requires-Dist: requests>=2.32.3
